LICENSE
MANIFEST.in
readme.rst
setup.cfg
setup.py
drf_friendly_errors_django_4.egg-info/PKG-INFO
drf_friendly_errors_django_4.egg-info/SOURCES.txt
drf_friendly_errors_django_4.egg-info/dependency_links.txt
drf_friendly_errors_django_4.egg-info/not-zip-safe
drf_friendly_errors_django_4.egg-info/top_level.txt
rest_framework_friendly_errors/__init__.py
rest_framework_friendly_errors/field_map.py
rest_framework_friendly_errors/handlers.py
rest_framework_friendly_errors/mixins.py
rest_framework_friendly_errors/settings.py
rest_framework_friendly_errors/utils.py